medial/__init__.py
medial/db.py
medial/db_postgres.py
medial/db_sqlite.py
medial/exceptions.py
medial/persistence.py
medial-0.4.6.dist-info/LICENSE
medial-0.4.6.dist-info/METADATA
medial-0.4.6.dist-info/WHEEL
medial-0.4.6.dist-info/top_level.txt
medial-0.4.6.dist-info/RECORD
