Metadata-Version: 2.1
Name: medial
Version: 0.4.6
Summary: Minimal database access library
Home-page: https://gitlab.com/dlek/medial
Author: dlek
Author-email: dlek@p0nk.net
Project-URL: Bug Tracker, https://gitlab.com/dlek/medial/-/issues
Classifier: Programming Language :: Python :: 3
Classifier: License :: OSI Approved :: MIT License
Classifier: Operating System :: OS Independent
Requires-Python: >=3.6
License-File: LICENSE
Requires-Dist: psycopg2-binary
